[[0.314235,{"lines":{"0":[["darya@elena-VirtualBox:~$                                      ",{}]],"1":[["                                                               ",{}]],"2":[["                                                               ",{}]],"3":[["                                                               ",{}]],"4":[["                                                               ",{}]],"5":[["                                                               ",{}]],"6":[["                                                               ",{}]],"7":[["                                                               ",{}]],"8":[["                                                               ",{}]],"9":[["                                                               ",{}]],"10":[["                                                               ",{}]],"11":[["                                                               ",{}]],"12":[["                                                               ",{}]],"13":[["                                                               ",{}]],"14":[["                                                               ",{}]],"15":[["                                                               ",{}]],"16":[["                                                               ",{}]],"17":[["                                                               ",{}]],"18":[["                                                               ",{}]],"19":[["                                                               ",{}]],"20":[["                                                               ",{}]],"21":[["                                                               ",{}]],"22":[["                                                               ",{}]],"23":[["                                                               ",{}]]},"cursor":{"x":26,"y":0,"visible":true}}],[2.284345,{"lines":{"0":[["darya@elena-VirtualBox:~$ t                                    ",{}]]},"cursor":{"x":27}}],[2.174189,{"lines":{"0":[["darya@elena-VirtualBox:~$ to                                   ",{}]]},"cursor":{"x":28}}],[0.273636,{"lines":{"0":[["darya@elena-VirtualBox:~$ tou                                  ",{}]]},"cursor":{"x":29}}],[0.316643,{"lines":{"0":[["darya@elena-VirtualBox:~$ touc                                 ",{}]]},"cursor":{"x":30}}],[0.154837,{"lines":{"0":[["darya@elena-VirtualBox:~$ touch                                ",{}]]},"cursor":{"x":31}}],[0.09739200000000001,{"cursor":{"x":32}}],[5.235149,{"cursor":{"x":31}}],[0.501039,{"lines":{"0":[["darya@elena-VirtualBox:~$ touc                                 ",{}]]},"cursor":{"x":30}}],[0.032062,{"lines":{"0":[["darya@elena-VirtualBox:~$ tou                                  ",{}]]},"cursor":{"x":29}}],[0.031966,{"lines":{"0":[["darya@elena-VirtualBox:~$ to                                   ",{}]]},"cursor":{"x":28}}],[0.031103,{"lines":{"0":[["darya@elena-VirtualBox:~$ t                                    ",{}]]},"cursor":{"x":27}}],[0.031475,{"lines":{"0":[["darya@elena-VirtualBox:~$                                      ",{}]]},"cursor":{"x":26}}],[0.029419,{}],[0.030323,{}],[0.031219,{}],[0.029397,{}],[0.032361,{}],[0.030715,{}],[0.030919,{}],[0.031491,{}],[0.030667,{}],[0.476573,{"lines":{"0":[["darya@elena-VirtualBox:~$ m                                    ",{}]]},"cursor":{"x":27}}],[0.485958,{"lines":{"0":[["darya@elena-VirtualBox:~$ mk                                   ",{}]]},"cursor":{"x":28}}],[0.699875,{"lines":{"0":[["darya@elena-VirtualBox:~$ mkd                                  ",{}]]},"cursor":{"x":29}}],[0.17832,{"lines":{"0":[["darya@elena-VirtualBox:~$ mkdi                                 ",{}]]},"cursor":{"x":30}}],[0.138969,{"lines":{"0":[["darya@elena-VirtualBox:~$ mkdir                                ",{}]]},"cursor":{"x":31}}],[2.133252,{"cursor":{"x":32}}],[1.169866,{"lines":{"0":[["darya@elena-VirtualBox:~$ mkdir w                              ",{}]]},"cursor":{"x":33}}],[0.217444,{"lines":{"0":[["darya@elena-VirtualBox:~$ mkdir ww                             ",{}]]},"cursor":{"x":34}}],[0.208267,{"lines":{"0":[["darya@elena-VirtualBox:~$ mkdir www                            ",{}]]},"cursor":{"x":35}}],[0.8462499999999999,{"cursor":{"x":0,"y":1}}],[0.020333,{"lines":{"1":[["darya@elena-VirtualBox:~$                                      ",{}]]},"cursor":{"x":26}}],[1.101515,{"lines":{"1":[["darya@elena-VirtualBox:~$ c                                    ",{}]]},"cursor":{"x":27}}],[0.119132,{"lines":{"1":[["darya@elena-VirtualBox:~$ cd                                   ",{}]]},"cursor":{"x":28}}],[0.236165,{"cursor":{"x":29}}],[0.422907,{"lines":{"1":[["darya@elena-VirtualBox:~$ cd w                                 ",{}]]},"cursor":{"x":30}}],[0.192968,{"lines":{"1":[["darya@elena-VirtualBox:~$ cd ww                                ",{}]]},"cursor":{"x":31}}],[0.159952,{"lines":{"1":[["darya@elena-VirtualBox:~$ cd www                               ",{}]]},"cursor":{"x":32}}],[0.923368,{"lines":{"2":[["darya@elena-VirtualBox:~/www$                                  ",{}]]},"cursor":{"x":30,"y":2}}],[1.529676,{"lines":{"2":[["darya@elena-VirtualBox:~/www$ m                                ",{}]]},"cursor":{"x":31}}],[0.6428739999999999,{"lines":{"2":[["darya@elena-VirtualBox:~/www$ mk                               ",{}]]},"cursor":{"x":32}}],[0.498468,{"lines":{"2":[["darya@elena-VirtualBox:~/www$ mkd                              ",{}]]},"cursor":{"x":33}}],[0.159013,{"lines":{"2":[["darya@elena-VirtualBox:~/www$ mkdi                             ",{}]]},"cursor":{"x":34}}],[0.600129,{"lines":{"2":[["darya@elena-VirtualBox:~/www$ mkdir                            ",{}]]},"cursor":{"x":35}}],[0.718305,{"cursor":{"x":36}}],[0.366243,{"lines":{"2":[["darya@elena-VirtualBox:~/www$ mkdir s                          ",{}]]},"cursor":{"x":37}}],[0.142505,{"lines":{"2":[["darya@elena-VirtualBox:~/www$ mkdir si                         ",{}]]},"cursor":{"x":38}}],[0.322064,{"lines":{"2":[["darya@elena-VirtualBox:~/www$ mkdir sit                        ",{}]]},"cursor":{"x":39}}],[0.11834,{"lines":{"2":[["darya@elena-VirtualBox:~/www$ mkdir site                       ",{}]]},"cursor":{"x":40}}],[0.316687,{"lines":{"2":[["darya@elena-VirtualBox:~/www$ mkdir site1                      ",{}]]},"cursor":{"x":41}}],[1.546696,{"cursor":{"x":0,"y":3}}],[0.000456,{"lines":{"3":[["darya@elena-VirtualBox:~/www$                                  ",{}]]},"cursor":{"x":30}}],[44.269077,{"lines":{"3":[["darya@elena-VirtualBox:~/www$ c                                ",{}]]},"cursor":{"x":31}}],[0.170235,{"lines":{"3":[["darya@elena-VirtualBox:~/www$ cd                               ",{}]]},"cursor":{"x":32}}],[0.879826,{"cursor":{"x":33}}],[0.392393,{"lines":{"3":[["darya@elena-VirtualBox:~/www$ cd s                             ",{}]]},"cursor":{"x":34}}],[0.167801,{"lines":{"3":[["darya@elena-VirtualBox:~/www$ cd si                            ",{}]]},"cursor":{"x":35}}],[0.307628,{"lines":{"3":[["darya@elena-VirtualBox:~/www$ cd sit                           ",{}]]},"cursor":{"x":36}}],[0.124785,{"lines":{"3":[["darya@elena-VirtualBox:~/www$ cd site                          ",{}]]},"cursor":{"x":37}}],[0.371675,{"lines":{"3":[["darya@elena-VirtualBox:~/www$ cd site1                         ",{}]]},"cursor":{"x":38}}],[0.537436,{"lines":{"4":[["darya@elena-VirtualBox:~/www/site1$                            ",{}]]},"cursor":{"x":36,"y":4}}],[1.254372,{"lines":{"4":[["darya@elena-VirtualBox:~/www/site1$ n                          ",{}]]},"cursor":{"x":37}}],[0.119948,{"lines":{"4":[["darya@elena-VirtualBox:~/www/site1$ na                         ",{}]]},"cursor":{"x":38}}],[0.125971,{"lines":{"4":[["darya@elena-VirtualBox:~/www/site1$ nan                        ",{}]]},"cursor":{"x":39}}],[0.153293,{"lines":{"4":[["darya@elena-VirtualBox:~/www/site1$ nano                       ",{}]]},"cursor":{"x":40}}],[0.187852,{"cursor":{"x":41}}],[0.883562,{"cursor":{"x":40}}],[0.501943,{"lines":{"4":[["darya@elena-VirtualBox:~/www/site1$ nan                        ",{}]]},"cursor":{"x":39}}],[0.032715,{"lines":{"4":[["darya@elena-VirtualBox:~/www/site1$ na                         ",{}]]},"cursor":{"x":38}}],[0.037361,{"lines":{"4":[["darya@elena-VirtualBox:~/www/site1$ n                          ",{}]]},"cursor":{"x":37}}],[0.037926,{"lines":{"4":[["darya@elena-VirtualBox:~/www/site1$                            ",{}]]},"cursor":{"x":36}}],[0.031214,{}],[0.03078,{}],[0.030842,{}],[0.030311,{}],[0.030026,{}],[0.029888,{}],[0.031302,{}],[0.030546,{}],[0.030866,{}],[0.376687,{"lines":{"4":[["darya@elena-VirtualBox:~/www/site1$ s                          ",{}]]},"cursor":{"x":37}}],[0.251474,{"lines":{"4":[["darya@elena-VirtualBox:~/www/site1$ su                         ",{}]]},"cursor":{"x":38}}],[0.711372,{"lines":{"4":[["darya@elena-VirtualBox:~/www/site1$ sud                        ",{}]]},"cursor":{"x":39}}],[0.112803,{"lines":{"4":[["darya@elena-VirtualBox:~/www/site1$ sudo                       ",{}]]},"cursor":{"x":40}}],[0.082632,{"cursor":{"x":41}}],[0.483252,{"lines":{"4":[["darya@elena-VirtualBox:~/www/site1$ sudo n                     ",{}]]},"cursor":{"x":42}}],[0.123177,{"lines":{"4":[["darya@elena-VirtualBox:~/www/site1$ sudo na                    ",{}]]},"cursor":{"x":43}}],[0.126631,{"lines":{"4":[["darya@elena-VirtualBox:~/www/site1$ sudo nan                   ",{}]]},"cursor":{"x":44}}],[0.227805,{"lines":{"4":[["darya@elena-VirtualBox:~/www/site1$ sudo nano                  ",{}]]},"cursor":{"x":45}}],[0.864138,{"cursor":{"x":46}}],[0.644614,{"lines":{"4":[["darya@elena-VirtualBox:~/www/site1$ sudo nano i                ",{}]]},"cursor":{"x":47}}],[0.207662,{"lines":{"4":[["darya@elena-VirtualBox:~/www/site1$ sudo nano in               ",{}]]},"cursor":{"x":48}}],[0.6325229999999999,{"lines":{"4":[["darya@elena-VirtualBox:~/www/site1$ sudo nano inf              ",{}]]},"cursor":{"x":49}}],[0.132276,{"lines":{"4":[["darya@elena-VirtualBox:~/www/site1$ sudo nano info             ",{}]]},"cursor":{"x":50}}],[1.229005,{"cursor":{"x":0,"y":5}}],[0.02084,{"lines":{"5":[["[sudo] password for darya:                                     ",{}]]},"cursor":{"x":27}}],[2.59553,{"cursor":{"x":0,"y":6}}],[0.150742,{"lines":{"0":[["                                                               ",{}]],"1":[["                                                               ",{}]],"2":[["                                                               ",{}]],"3":[["                                                               ",{}]],"4":[["                                                               ",{}]],"5":[["                                                               ",{}]]}}],[0.001071,{"lines":{"0":[["  GNU nano 2.2.6          Файл: info                           ",{"inverse":true}]],"21":[["                        ",{}],["[ Новый файл ]",{"inverse":true}],["                         ",{}]],"22":[["^G",{"inverse":true}],[" Помощь ",{}],["^O",{"inverse":true}],[" Записат",{}],["^R",{"inverse":true}],[" ЧитФайл",{}],["^Y",{"inverse":true}],[" ПредCтр",{}],["^K",{"inverse":true}],[" Вырезат",{}],["^C",{"inverse":true}],[" ТекПозиц  ",{}]],"23":[["^X",{"inverse":true}],[" Выход  ",{}],["^J",{"inverse":true}],[" Выровня",{}],["^W",{"inverse":true}],[" Поиск  ",{}],["^V",{"inverse":true}],[" СледCтр",{}],["^U",{"inverse":true}],[" ОтмВыре",{}],["^T",{"inverse":true}],[" Словарь   ",{}]]},"cursor":{"y":2}}],[7.010016,{"lines":{"0":[["  GNU nano 2.2.6          Файл: info                  Изменён  ",{"inverse":true}]],"2":[["<                                                              ",{}]]},"cursor":{"x":1}}],[2.679281,{"lines":{"2":[["<&                                                             ",{}]]},"cursor":{"x":2}}],[1.148179,{"lines":{"2":[["<                                                              ",{}]]},"cursor":{"x":1}}],[3.21879,{"lines":{"2":[["<?                                                             ",{}]]},"cursor":{"x":2}}],[1.466471,{"cursor":{"x":3}}],[0.53111,{"lines":{"2":[["<? p                                                           ",{}]]},"cursor":{"x":4}}],[0.10418,{"lines":{"2":[["<? ph                                                          ",{}]]},"cursor":{"x":5}}],[0.09202399999999999,{"lines":{"2":[["<? php                                                         ",{}]]},"cursor":{"x":6}}],[2.007889,{"cursor":{"x":7}}],[0.342557,{"lines":{"2":[["<? php p                                                       ",{}]]},"cursor":{"x":8}}],[1.509396,{"lines":{"2":[["<? php ph                                                      ",{}]]},"cursor":{"x":9}}],[0.142653,{"lines":{"2":[["<? php php                                                     ",{}]]},"cursor":{"x":10}}],[0.429636,{"lines":{"2":[["<? php phpi                                                    ",{}]]},"cursor":{"x":11}}],[0.263236,{"lines":{"2":[["<? php phpin                                                   ",{}]]},"cursor":{"x":12}}],[0.400847,{"lines":{"2":[["<? php phpinf                                                  ",{}]]},"cursor":{"x":13}}],[0.293175,{"lines":{"2":[["<? php phpinfo                                                 ",{}]]},"cursor":{"x":14}}],[0.37352,{"lines":{"2":[["<? php phpinfo(                                                ",{}]]},"cursor":{"x":15}}],[0.292842,{"lines":{"2":[["<? php phpinfo()                                               ",{}]]},"cursor":{"x":16}}],[1.767376,{"lines":{"2":[["<? php phpinfo();                                              ",{}]]},"cursor":{"x":17}}],[1.540824,{"cursor":{"x":18}}],[1.739578,{"lines":{"2":[["<? php phpinfo(); ?                                            ",{}]]},"cursor":{"x":19}}],[1.6881,{"lines":{"2":[["<? php phpinfo(); ?.                                           ",{}]]},"cursor":{"x":20}}],[0.453499,{"lines":{"2":[["<? php phpinfo(); ?                                            ",{}]]},"cursor":{"x":19}}],[0.393032,{"lines":{"2":[["<? php phpinfo(); ?>                                           ",{}]]},"cursor":{"x":20}}],[4.347979,{"lines":{"21":[["Сохранить изменённый буфер? (ИНАЧЕ ВСЕ ИЗМЕНЕНИЯ БУДУТ ПОТЕРЯН ",{"inverse":true}]],"22":[[" Y",{"inverse":true}],[" Да                                                          ",{}]],"23":[[" N",{"inverse":true}],[" Нет          ",{}],["^C",{"inverse":true}],[" Отмена                                      ",{}]]},"cursor":{"x":62,"y":21}}],[1.856552,{"lines":{"21":[["Имя файла для записи: info                                     ",{"inverse":true}]],"22":[["^G",{"inverse":true}],[" Помощь      ",{}],["M-D",{"inverse":true}],[" Формат DOS ",{}],["M-A",{"inverse":true}],[" Доп. в нача",{}],["M-B",{"inverse":true}],[" Резерв. копия ",{}]],"23":[["^C",{"inverse":true}],[" Отмена      ",{}],["M-M",{"inverse":true}],[" Формат Mac ",{}],["M-P",{"inverse":true}],[" Доп. в конец                 ",{}]]},"cursor":{"x":26}}],[2.510292,{"lines":{"0":[["  GNU nano 2.2.6          Файл: info                           ",{"inverse":true}]],"21":[["                     ",{}],["[ Записано 1 строка ]",{"inverse":true}],["                     ",{}]],"22":[["                                                               ",{}]],"23":[["                                                               ",{}]]},"cursor":{"x":62,"y":23}}],[0.020795,{"lines":{"0":[["darya@elena-VirtualBox:~$ mkdir www                            ",{}]],"1":[["darya@elena-VirtualBox:~$ cd www                               ",{}]],"2":[["darya@elena-VirtualBox:~/www$ mkdir site1                      ",{}]],"3":[["darya@elena-VirtualBox:~/www$ cd site1                         ",{}]],"4":[["darya@elena-VirtualBox:~/www/site1$ sudo nano info             ",{}]],"5":[["[sudo] password for darya:                                     ",{}]],"6":[["darya@elena-VirtualBox:~/www/site1$                            ",{}]],"21":[["                                                               ",{}]]},"cursor":{"x":36,"y":6}}],[44.906253,{"lines":{"6":[["darya@elena-VirtualBox:~/www/site1$ c                          ",{}]]},"cursor":{"x":37}}],[0.117377,{"lines":{"6":[["darya@elena-VirtualBox:~/www/site1$ cd                         ",{}]]},"cursor":{"x":38}}],[0.324304,{"cursor":{"x":39}}],[0.546879,{"lines":{"6":[["darya@elena-VirtualBox:~/www/site1$ cd ~                       ",{}]]},"cursor":{"x":40}}],[0.375826,{"lines":{"7":[["darya@elena-VirtualBox:~$                                      ",{}]]},"cursor":{"x":26,"y":7}}],[7.67199,{"lines":{"7":[["darya@elena-VirtualBox:~$ s                                    ",{}]]},"cursor":{"x":27}}],[0.252886,{"lines":{"7":[["darya@elena-VirtualBox:~$ su                                   ",{}]]},"cursor":{"x":28}}],[0.34763,{"lines":{"7":[["darya@elena-VirtualBox:~$ sud                                  ",{}]]},"cursor":{"x":29}}],[0.114956,{"lines":{"7":[["darya@elena-VirtualBox:~$ sudo                                 ",{}]]},"cursor":{"x":30}}],[1.225632,{"cursor":{"x":31}}],[0.453775,{"lines":{"7":[["darya@elena-VirtualBox:~$ sudo c                               ",{}]]},"cursor":{"x":32}}],[0.184511,{"lines":{"7":[["darya@elena-VirtualBox:~$ sudo cp                              ",{}]]},"cursor":{"x":33}}],[0.773501,{"cursor":{"x":34}}],[0.948017,{"lines":{"7":[["darya@elena-VirtualBox:~$ sudo cp /                            ",{}]]},"cursor":{"x":35}}],[0.983166,{"lines":{"7":[["darya@elena-VirtualBox:~$ sudo cp /e                           ",{}]]},"cursor":{"x":36}}],[0.471012,{"lines":{"7":[["darya@elena-VirtualBox:~$ sudo cp /etc/                        ",{}]]},"cursor":{"x":39}}],[0.152585,{}],[1.857831,{"lines":{"7":[["darya@elena-VirtualBox:~$ sudo cp /etc/a                       ",{}]]},"cursor":{"x":40}}],[0.185052,{"lines":{"7":[["darya@elena-VirtualBox:~$ sudo cp /etc/ap                      ",{}]]},"cursor":{"x":41}}],[0.5852579999999999,{"lines":{"7":[["darya@elena-VirtualBox:~$ sudo cp /etc/apa                     ",{}]]},"cursor":{"x":42}}],[0.382943,{"lines":{"7":[["darya@elena-VirtualBox:~$ sudo cp /etc/apache2/                ",{}]]},"cursor":{"x":47}}],[2.083887,{"lines":{"7":[["darya@elena-VirtualBox:~$ sudo cp /etc/apache2/s               ",{}]]},"cursor":{"x":48}}],[0.348748,{"lines":{"7":[["darya@elena-VirtualBox:~$ sudo cp /etc/apache2/si              ",{}]]},"cursor":{"x":49}}],[0.844122,{"lines":{"7":[["darya@elena-VirtualBox:~$ sudo cp /etc/apache2/sit             ",{}]]},"cursor":{"x":50}}],[0.132702,{"lines":{"7":[["darya@elena-VirtualBox:~$ sudo cp /etc/apache2/site            ",{}]]},"cursor":{"x":51}}],[0.343691,{"lines":{"7":[["darya@elena-VirtualBox:~$ sudo cp /etc/apache2/sites           ",{}]]},"cursor":{"x":52}}],[1.008834,{"lines":{"7":[["darya@elena-VirtualBox:~$ sudo cp /etc/apache2/sites-          ",{}]]},"cursor":{"x":53}}],[1.092283,{"lines":{"7":[["darya@elena-VirtualBox:~$ sudo cp /etc/apache2/sites-a         ",{}]]},"cursor":{"x":54}}],[0.463093,{"lines":{"7":[["darya@elena-VirtualBox:~$ sudo cp /etc/apache2/sites-available/",{}]]},"cursor":{"x":0,"y":8}}],[2.331789,{"lines":{"8":[["d                                                              ",{}]]},"cursor":{"x":1}}],[1.711365,{}],[0.000191,{"lines":{"8":[["default                                                        ",{}]]},"cursor":{"x":7}}],[2.320086,{"cursor":{"x":8}}],[0.869719,{"lines":{"8":[["default /                                                      ",{}]]},"cursor":{"x":9}}],[0.724851,{"lines":{"8":[["default /e                                                     ",{}]]},"cursor":{"x":10}}],[0.236176,{"lines":{"8":[["default /etc/                                                  ",{}]]},"cursor":{"x":13}}],[1.719733,{"lines":{"8":[["default /etc/a                                                 ",{}]]},"cursor":{"x":14}}],[0.203834,{"lines":{"8":[["default /etc/ap                                                ",{}]]},"cursor":{"x":15}}],[0.113434,{"lines":{"8":[["default /etc/apa                                               ",{}]]},"cursor":{"x":16}}],[0.359854,{"lines":{"8":[["default /etc/apache2/                                          ",{}]]},"cursor":{"x":21}}],[2.787735,{"lines":{"8":[["default /etc/apache2/s                                         ",{}]]},"cursor":{"x":22}}],[0.232935,{"lines":{"8":[["default /etc/apache2/si                                        ",{}]]},"cursor":{"x":23}}],[0.212897,{}],[0.000146,{"lines":{"8":[["default /etc/apache2/sites-                                    ",{}]]},"cursor":{"x":27}}],[1.814761,{"lines":{"8":[["default /etc/apache2/sites-a                                   ",{}]]},"cursor":{"x":28}}],[0.349355,{"lines":{"8":[["default /etc/apache2/sites-available/                          ",{}]]},"cursor":{"x":37}}],[1.962812,{"lines":{"8":[["default /etc/apache2/sites-available/s                         ",{}]]},"cursor":{"x":38}}],[0.645367,{"lines":{"8":[["default /etc/apache2/sites-available/si                        ",{}]]},"cursor":{"x":39}}],[0.705704,{"lines":{"8":[["default /etc/apache2/sites-available/sit                       ",{}]]},"cursor":{"x":40}}],[0.098372,{"lines":{"8":[["default /etc/apache2/sites-available/site                      ",{}]]},"cursor":{"x":41}}],[0.269079,{"lines":{"8":[["default /etc/apache2/sites-available/site1                     ",{}]]},"cursor":{"x":42}}],[1.922432,{"cursor":{"x":0,"y":9}}],[0.045066,{"lines":{"9":[["darya@elena-VirtualBox:~$                                      ",{}]]},"cursor":{"x":26}}],[4.03797,{"lines":{"9":[["darya@elena-VirtualBox:~$ s                                    ",{}]]},"cursor":{"x":27}}],[0.168546,{"lines":{"9":[["darya@elena-VirtualBox:~$ su                                   ",{}]]},"cursor":{"x":28}}],[0.188646,{"lines":{"9":[["darya@elena-VirtualBox:~$ sud                                  ",{}]]},"cursor":{"x":29}}],[0.235655,{"lines":{"9":[["darya@elena-VirtualBox:~$ sudo                                 ",{}]]},"cursor":{"x":30}}],[1.14171,{"cursor":{"x":31}}],[2.485823,{"lines":{"9":[["darya@elena-VirtualBox:~$ sudo n                               ",{}]]},"cursor":{"x":32}}],[0.099425,{"lines":{"9":[["darya@elena-VirtualBox:~$ sudo na                              ",{}]]},"cursor":{"x":33}}],[0.596871,{"lines":{"9":[["darya@elena-VirtualBox:~$ sudo nan                             ",{}]]},"cursor":{"x":34}}],[0.199796,{"lines":{"9":[["darya@elena-VirtualBox:~$ sudo nano                            ",{}]]},"cursor":{"x":35}}],[1.87104,{"lines":{"9":[["darya@elena-VirtualBox:~$ sudo nan                             ",{}]]},"cursor":{"x":34}}],[0.500771,{"lines":{"9":[["darya@elena-VirtualBox:~$ sudo na                              ",{}]]},"cursor":{"x":33}}],[0.031374,{"lines":{"9":[["darya@elena-VirtualBox:~$ sudo n                               ",{}]]},"cursor":{"x":32}}],[0.037567,{"lines":{"9":[["darya@elena-VirtualBox:~$ sudo                                 ",{}]]},"cursor":{"x":31}}],[0.029969,{"cursor":{"x":30}}],[0.031752,{"lines":{"9":[["darya@elena-VirtualBox:~$ sud                                  ",{}]]},"cursor":{"x":29}}],[0.029906,{"lines":{"9":[["darya@elena-VirtualBox:~$ su                                   ",{}]]},"cursor":{"x":28}}],[0.031707,{"lines":{"9":[["darya@elena-VirtualBox:~$ s                                    ",{}]]},"cursor":{"x":27}}],[0.030132,{"lines":{"9":[["darya@elena-VirtualBox:~$                                      ",{}]]},"cursor":{"x":26}}],[0.032011,{}],[0.029596,{}],[0.031074,{}],[0.031072,{}],[0.031706,{}],[0.03255,{}],[0.03087,{}],[1.739705,{"lines":{"9":[["darya@elena-VirtualBox:~$ s                                    ",{}]]},"cursor":{"x":27}}],[0.189583,{"lines":{"9":[["darya@elena-VirtualBox:~$ si                                   ",{}]]},"cursor":{"x":28}}],[1.011861,{"lines":{"9":[["darya@elena-VirtualBox:~$ s                                    ",{}]]},"cursor":{"x":27}}],[0.471807,{"lines":{"9":[["darya@elena-VirtualBox:~$ su                                   ",{}]]},"cursor":{"x":28}}],[0.198274,{"lines":{"9":[["darya@elena-VirtualBox:~$ sud                                  ",{}]]},"cursor":{"x":29}}],[0.360116,{"lines":{"9":[["darya@elena-VirtualBox:~$ sudo                                 ",{}]]},"cursor":{"x":30}}],[0.145946,{"cursor":{"x":31}}],[0.779969,{"lines":{"9":[["darya@elena-VirtualBox:~$ sudo n                               ",{}]]},"cursor":{"x":32}}],[0.092032,{"lines":{"9":[["darya@elena-VirtualBox:~$ sudo na                              ",{}]]},"cursor":{"x":33}}],[0.155688,{"lines":{"9":[["darya@elena-VirtualBox:~$ sudo nan                             ",{}]]},"cursor":{"x":34}}],[0.256629,{"lines":{"9":[["darya@elena-VirtualBox:~$ sudo nano                            ",{}]]},"cursor":{"x":35}}],[1.99734,{"cursor":{"x":36}}],[0.632142,{"lines":{"9":[["darya@elena-VirtualBox:~$ sudo nano /                          ",{}]]},"cursor":{"x":37}}],[0.283218,{"lines":{"9":[["darya@elena-VirtualBox:~$ sudo nano /e                         ",{}]]},"cursor":{"x":38}}],[0.397252,{"lines":{"9":[["darya@elena-VirtualBox:~$ sudo nano /etc/                      ",{}]]},"cursor":{"x":41}}],[0.495788,{"lines":{"9":[["darya@elena-VirtualBox:~$ sudo nano /etc//                     ",{}]]},"cursor":{"x":42}}],[0.72361,{"lines":{"9":[["darya@elena-VirtualBox:~$ sudo nano /etc/                      ",{}]]},"cursor":{"x":41}}],[1.265109,{"lines":{"9":[["darya@elena-VirtualBox:~$ sudo nano /etc/a                     ",{}]]},"cursor":{"x":42}}],[0.098977,{"lines":{"9":[["darya@elena-VirtualBox:~$ sudo nano /etc/ap                    ",{}]]},"cursor":{"x":43}}],[0.126012,{"lines":{"9":[["darya@elena-VirtualBox:~$ sudo nano /etc/apa                   ",{}]]},"cursor":{"x":44}}],[0.25418,{"lines":{"9":[["darya@elena-VirtualBox:~$ sudo nano /etc/apache2/              ",{}]]},"cursor":{"x":49}}],[1.552068,{"lines":{"9":[["darya@elena-VirtualBox:~$ sudo nano /etc/apache2/s             ",{}]]},"cursor":{"x":50}}],[0.322136,{}],[0.000302,{"lines":{"9":[["darya@elena-VirtualBox:~$ sudo nano /etc/apache2/sites-        ",{}]]},"cursor":{"x":55}}],[1.630277,{"lines":{"9":[["darya@elena-VirtualBox:~$ sudo nano /etc/apache2/sites-a       ",{}]]},"cursor":{"x":56}}],[0.142018,{"lines":{"9":[["darya@elena-VirtualBox:~$ sudo nano /etc/apache2/sites-availabl",{}]],"10":[["e/                                                             ",{}]]},"cursor":{"x":2,"y":10}}],[2.438006,{"lines":{"10":[["e/s                                                            ",{}]]},"cursor":{"x":3}}],[0.448972,{"lines":{"10":[["e/site1                                                        ",{}]]},"cursor":{"x":8}}],[2.036135,{"cursor":{"x":0,"y":11}}],[0.05417,{"lines":{"0":[["                                                               ",{}]],"1":[["                                                               ",{}]],"2":[["                                                               ",{}]],"3":[["                                                               ",{}]],"4":[["                                                               ",{}]],"5":[["                                                               ",{}]],"6":[["                                                               ",{}]],"7":[["                                                               ",{}]],"8":[["                                                               ",{}]],"9":[["                                                               ",{}]],"10":[["                                                               ",{}]]}}],[0.016367,{"lines":{"0":[["  GNU nano 2.2.6 Файл: ...ache2/sites-available/site1          ",{"inverse":true}]],"2":[["<VirtualHost *:80>                                             ",{}]],"3":[["        ServerAdmin webmaster@localhost                        ",{}]],"5":[["        DocumentRoot /var/www                                  ",{}]],"6":[["        <Directory />                                          ",{}]],"7":[["                Options FollowSymLinks                         ",{}]],"8":[["                AllowOverride None                             ",{}]],"9":[["        </Directory>                                           ",{}]],"10":[["        <Directory /var/www/>                                  ",{}]],"11":[["                Options Indexes FollowSymLinks MultiViews      ",{}]],"12":[["                AllowOverride None                             ",{}]],"13":[["                Order allow,deny                               ",{}]],"14":[["                allow from all                                 ",{}]],"15":[["        </Directory>                                           ",{}]],"17":[["        ScriptAlias /cgi-bin/ /usr/lib/cgi-bin/                ",{}]],"18":[["        <Directory \"/usr/lib/cgi-bin\">                         ",{}]],"19":[["                AllowOverride None                             ",{}]],"20":[["                Options +ExecCGI -MultiViews +SymLinksIfOwnerM$",{}]],"21":[["                    ",{}],["[ Прочитана 31 строка ]",{"inverse":true}],["                    ",{}]],"22":[["^G",{"inverse":true}],[" Помощь ",{}],["^O",{"inverse":true}],[" Записат",{}],["^R",{"inverse":true}],[" ЧитФайл",{}],["^Y",{"inverse":true}],[" ПредCтр",{}],["^K",{"inverse":true}],[" Вырезат",{}],["^C",{"inverse":true}],[" ТекПозиц  ",{}]],"23":[["^X",{"inverse":true}],[" Выход  ",{}],["^J",{"inverse":true}],[" Выровня",{}],["^W",{"inverse":true}],[" Поиск  ",{}],["^V",{"inverse":true}],[" СледCтр",{}],["^U",{"inverse":true}],[" ОтмВыре",{}],["^T",{"inverse":true}],[" Словарь   ",{}]]},"cursor":{"y":2}}],[4.804094,{"cursor":{"y":3}}],[0.299244,{"cursor":{"y":4}}],[0.506151,{"cursor":{"y":5}}],[0.405422,{"cursor":{"x":8}}],[0.501922,{"cursor":{"x":9}}],[0.032472,{"cursor":{"x":10}}],[0.031266,{"cursor":{"x":11}}],[0.036484,{"cursor":{"x":12}}],[0.022546,{"cursor":{"x":13}}],[0.032997,{"cursor":{"x":14}}],[0.030763,{"cursor":{"x":15}}],[0.029964,{"cursor":{"x":16}}],[0.031379,{"cursor":{"x":17}}],[0.038896,{"cursor":{"x":18}}],[0.189158,{"cursor":{"x":19}}],[0.501429,{"cursor":{"x":20}}],[0.031113,{"cursor":{"x":21}}],[0.033112,{"cursor":{"x":22}}],[0.029473,{"cursor":{"x":23}}],[0.031226,{"cursor":{"x":24}}],[0.03658,{"cursor":{"x":25}}],[0.03164,{"cursor":{"x":26}}],[0.03228,{"cursor":{"x":27}}],[0.031463,{"cursor":{"x":28}}],[0.029342,{"cursor":{"x":29}}],[0.03881,{"lines":{"21":[["                                                               ",{}]]},"cursor":{"x":0,"y":6}}],[0.332122,{"cursor":{"x":8}}],[0.955129,{"cursor":{"x":0}}],[0.334952,{"cursor":{"x":29,"y":5}}],[2.859285,{"lines":{"0":[["  GNU nano 2.2.6 Файл: ...ache2/sites-available/site1 Изменён  ",{"inverse":true}]],"5":[["        DocumentRoot /var/ww                                   ",{}]]},"cursor":{"x":28}}],[0.20328,{"lines":{"5":[["        DocumentRoot /var/w                                    ",{}]]},"cursor":{"x":27}}],[0.184037,{"lines":{"5":[["        DocumentRoot /var/                                     ",{}]]},"cursor":{"x":26}}],[0.158926,{"lines":{"5":[["        DocumentRoot /var                                      ",{}]]},"cursor":{"x":25}}],[0.158748,{"lines":{"5":[["        DocumentRoot /va                                       ",{}]]},"cursor":{"x":24}}],[0.168327,{"lines":{"5":[["        DocumentRoot /v                                        ",{}]]},"cursor":{"x":23}}],[0.461483,{"lines":{"5":[["        DocumentRoot /                                         ",{}]]},"cursor":{"x":22}}],[0.704986,{"lines":{"5":[["        DocumentRoot /h                                        ",{}]]},"cursor":{"x":23}}],[0.145691,{"lines":{"5":[["        DocumentRoot /ho                                       ",{}]]},"cursor":{"x":24}}],[0.256053,{"lines":{"5":[["        DocumentRoot /hom                                      ",{}]]},"cursor":{"x":25}}],[0.185629,{"lines":{"5":[["        DocumentRoot /home                                     ",{}]]},"cursor":{"x":26}}],[0.535091,{"lines":{"5":[["        DocumentRoot /home/                                    ",{}]]},"cursor":{"x":27}}],[0.799742,{"lines":{"5":[["        DocumentRoot /home/d                                   ",{}]]},"cursor":{"x":28}}],[0.121818,{"lines":{"5":[["        DocumentRoot /home/da                                  ",{}]]},"cursor":{"x":29}}],[0.398294,{"lines":{"5":[["        DocumentRoot /home/dar                                 ",{}]]},"cursor":{"x":30}}],[1.677224,{"lines":{"5":[["        DocumentRoot /home/dary                                ",{}]]},"cursor":{"x":31}}],[0.15363,{"lines":{"5":[["        DocumentRoot /home/darya                               ",{}]]},"cursor":{"x":32}}],[0.436882,{"lines":{"5":[["        DocumentRoot /home/darya/                              ",{}]]},"cursor":{"x":33}}],[2.190763,{"lines":{"5":[["        DocumentRoot /home/darya/w                             ",{}]]},"cursor":{"x":34}}],[0.192836,{"lines":{"5":[["        DocumentRoot /home/darya/ww                            ",{}]]},"cursor":{"x":35}}],[0.159542,{"lines":{"5":[["        DocumentRoot /home/darya/www                           ",{}]]},"cursor":{"x":36}}],[0.192431,{"lines":{"5":[["        DocumentRoot /home/darya/www/                          ",{}]]},"cursor":{"x":37}}],[1.59907,{"lines":{"5":[["        DocumentRoot /home/darya/www/s                         ",{}]]},"cursor":{"x":38}}],[0.188086,{"lines":{"5":[["        DocumentRoot /home/darya/www/si                        ",{}]]},"cursor":{"x":39}}],[0.501667,{"lines":{"5":[["        DocumentRoot /home/darya/www/sit                       ",{}]]},"cursor":{"x":40}}],[0.134188,{"lines":{"5":[["        DocumentRoot /home/darya/www/site                      ",{}]]},"cursor":{"x":41}}],[0.311919,{"lines":{"5":[["        DocumentRoot /home/darya/www/site1                     ",{}]]},"cursor":{"x":42}}],[0.779979,{"lines":{"5":[["        DocumentRoot /home/darya/www/site1/                    ",{}]]},"cursor":{"x":43}}],[7.82438,{"cursor":{"x":0,"y":4}}],[1.082001,{"cursor":{"x":8}}],[2.139275,{"lines":{"4":[["        S                                                      ",{}]]},"cursor":{"x":9}}],[0.284094,{"lines":{"4":[["        Se                                                     ",{}]]},"cursor":{"x":10}}],[0.147185,{"lines":{"4":[["        Ser                                                    ",{}]]},"cursor":{"x":11}}],[0.287995,{"lines":{"4":[["        Serv                                                   ",{}]]},"cursor":{"x":12}}],[0.1167,{"lines":{"4":[["        Serve                                                  ",{}]]},"cursor":{"x":13}}],[0.14431,{"lines":{"4":[["        Server                                                 ",{}]]},"cursor":{"x":14}}],[0.498338,{"lines":{"4":[["        ServerN                                                ",{}]]},"cursor":{"x":15}}],[0.168317,{"lines":{"4":[["        ServerNa                                               ",{}]]},"cursor":{"x":16}}],[0.13862,{"lines":{"4":[["        ServerNam                                              ",{}]]},"cursor":{"x":17}}],[0.149938,{"lines":{"4":[["        ServerName                                             ",{}]]},"cursor":{"x":18}}],[2.04436,{"cursor":{"x":19}}],[0.587014,{"lines":{"4":[["        ServerName s                                           ",{}]]},"cursor":{"x":20}}],[0.183346,{"lines":{"4":[["        ServerName si                                          ",{}]]},"cursor":{"x":21}}],[0.301634,{"lines":{"4":[["        ServerName sit                                         ",{}]]},"cursor":{"x":22}}],[0.103182,{"lines":{"4":[["        ServerName site                                        ",{}]]},"cursor":{"x":23}}],[0.30883,{"lines":{"4":[["        ServerName site1                                       ",{}]]},"cursor":{"x":24}}],[7.276114,{"cursor":{"y":5}}],[0.149814,{"cursor":{"x":21,"y":6}}],[0.165061,{"cursor":{"x":24,"y":7}}],[0.157862,{"cursor":{"y":8}}],[0.288114,{"cursor":{"x":20,"y":9}}],[0.39188,{"cursor":{"x":24,"y":10}}],[0.37848,{"cursor":{"x":25}}],[0.183592,{"cursor":{"x":26}}],[0.168895,{"cursor":{"x":27}}],[0.296718,{"cursor":{"x":28}}],[1.242793,{"cursor":{"x":27}}],[0.212337,{"cursor":{"x":26}}],[0.147781,{"cursor":{"x":25}}],[0.138484,{"cursor":{"x":24}}],[0.189991,{"cursor":{"x":23}}],[0.367675,{"lines":{"10":[["        <Directory /va/www/>                                   ",{}]]},"cursor":{"x":22}}],[0.450405,{"lines":{"10":[["        <Directory /v/www/>                                    ",{}]]},"cursor":{"x":21}}],[0.477243,{"lines":{"10":[["        <Directory //www/>                                     ",{}]]},"cursor":{"x":20}}],[1.0231,{"lines":{"10":[["        <Directory /h/www/>                                    ",{}]]},"cursor":{"x":21}}],[0.150081,{"lines":{"10":[["        <Directory /ho/www/>                                   ",{}]]},"cursor":{"x":22}}],[0.685895,{"lines":{"10":[["        <Directory /hom/www/>                                  ",{}]]},"cursor":{"x":23}}],[0.125681,{"lines":{"10":[["        <Directory /home/www/>                                 ",{}]]},"cursor":{"x":24}}],[0.332675,{"lines":{"10":[["        <Directory /home//www/>                                ",{}]]},"cursor":{"x":25}}],[0.267273,{"lines":{"10":[["        <Directory /home/d/www/>                               ",{}]]},"cursor":{"x":26}}],[0.213972,{"lines":{"10":[["        <Directory /home/da/www/>                              ",{}]]},"cursor":{"x":27}}],[0.258356,{"lines":{"10":[["        <Directory /home/dar/www/>                             ",{}]]},"cursor":{"x":28}}],[0.12215,{"lines":{"10":[["        <Directory /home/dary/www/>                            ",{}]]},"cursor":{"x":29}}],[0.174809,{"lines":{"10":[["        <Directory /home/darya/www/>                           ",{}]]},"cursor":{"x":30}}],[1.55406,{"cursor":{"x":31}}],[0.210587,{"cursor":{"x":32}}],[0.137944,{"cursor":{"x":33}}],[0.173495,{"cursor":{"x":34}}],[0.351927,{"cursor":{"x":35}}],[1.355759,{"lines":{"10":[["        <Directory /home/darya/www/s>                          ",{}]]},"cursor":{"x":36}}],[0.182593,{"lines":{"10":[["        <Directory /home/darya/www/si>                         ",{}]]},"cursor":{"x":37}}],[0.835546,{"lines":{"10":[["        <Directory /home/darya/www/sit>                        ",{}]]},"cursor":{"x":38}}],[0.116224,{"lines":{"10":[["        <Directory /home/darya/www/site>                       ",{}]]},"cursor":{"x":39}}],[0.260426,{"lines":{"10":[["        <Directory /home/darya/www/site1>                      ",{}]]},"cursor":{"x":40}}],[0.36977,{"lines":{"10":[["        <Directory /home/darya/www/site1/>                     ",{}]]},"cursor":{"x":41}}],[4.684554,{"cursor":{"x":32,"y":13}}],[0.228435,{"cursor":{"x":0,"y":16}}],[0.131299,{"cursor":{"x":34,"y":19}}],[1.088282,{"cursor":{"x":41,"y":20}}],[0.1773,{"lines":{"2":[["                AllowOverride None                             ",{}]],"3":[["                Order allow,deny                               ",{}]],"4":[["                allow from all                                 ",{}]],"5":[["        </Directory>                                           ",{}]],"6":[["                                                               ",{}]],"7":[["        ScriptAlias /cgi-bin/ /usr/lib/cgi-bin/                ",{}]],"8":[["        <Directory \"/usr/lib/cgi-bin\">                         ",{}]],"9":[["                AllowOverride None                             ",{}]],"10":[["                Options +ExecCGI -MultiViews +SymLinksIfOwnerM$",{}]],"11":[["                Order allow,deny                               ",{}]],"12":[["                Allow from all                                 ",{}]],"13":[["        </Directory>                                           ",{}]],"14":[["                                                               ",{}]],"15":[["        ErrorLog ${APACHE_LOG_DIR}/error.log                   ",{}]],"17":[["        # Possible values include: debug, info, notice, warn, $",{}]],"18":[["        # alert, emerg.                                        ",{}]],"19":[["        LogLevel warn                                          ",{}]],"20":[["                                                               ",{}]]},"cursor":{"x":32,"y":11}}],[0.165536,{"cursor":{"x":30,"y":12}}],[1.586903,{"cursor":{"x":20,"y":13}}],[0.198038,{"cursor":{"x":0,"y":14}}],[0.184315,{"cursor":{"x":41,"y":15}}],[0.165358,{"cursor":{"x":0,"y":16}}],[0.152793,{"cursor":{"x":41,"y":17}}],[0.164452,{"cursor":{"x":23,"y":18}}],[0.173174,{"cursor":{"x":21,"y":19}}],[0.193542,{"cursor":{"x":0,"y":20}}],[0.192768,{"lines":{"2":[["                Allow from all                                 ",{}]],"3":[["        </Directory>                                           ",{}]],"4":[["                                                               ",{}]],"5":[["        ErrorLog ${APACHE_LOG_DIR}/error.log                   ",{}]],"7":[["        # Possible values include: debug, info, notice, warn, $",{}]],"8":[["        # alert, emerg.                                        ",{}]],"9":[["        LogLevel warn                                          ",{}]],"10":[["                                                               ",{}]],"11":[["        CustomLog ${APACHE_LOG_DIR}/access.log combined        ",{}]],"12":[["</VirtualHost>                                                 ",{}]],"13":[["                                                               ",{}]],"15":[["                                                               ",{}]],"17":[["                                                               ",{}]],"18":[["                                                               ",{}]],"19":[["                                                               ",{}]]},"cursor":{"x":41,"y":11}}],[0.198839,{"cursor":{"x":14,"y":12}}],[1.013746,{"cursor":{"x":41,"y":11}}],[0.50003,{"cursor":{"x":0,"y":10}}],[0.051529,{"cursor":{"x":21,"y":9}}],[0.029736,{"cursor":{"x":23,"y":8}}],[0.029317,{"cursor":{"x":41,"y":7}}],[0.030893,{"cursor":{"x":0,"y":6}}],[0.032488,{"cursor":{"x":41,"y":5}}],[0.03879,{"cursor":{"x":0,"y":4}}],[0.022967,{"cursor":{"x":20,"y":3}}],[0.030372,{"cursor":{"x":30,"y":2}}],[0.068407,{"lines":{"2":[["                AllowOverride None                             ",{}]],"3":[["                Order allow,deny                               ",{}]],"4":[["                allow from all                                 ",{}]],"5":[["        </Directory>                                           ",{}]],"7":[["        ScriptAlias /cgi-bin/ /usr/lib/cgi-bin/                ",{}]],"8":[["        <Directory \"/usr/lib/cgi-bin\">                         ",{}]],"9":[["                AllowOverride None                             ",{}]],"10":[["                Options +ExecCGI -MultiViews +SymLinksIfOwnerM$",{}]],"11":[["                Order allow,deny                               ",{}]],"12":[["                Allow from all                                 ",{}]],"13":[["        </Directory>                                           ",{}]],"15":[["        ErrorLog ${APACHE_LOG_DIR}/error.log                   ",{}]],"17":[["        # Possible values include: debug, info, notice, warn, $",{}]],"18":[["        # alert, emerg.                                        ",{}]],"19":[["        LogLevel warn                                          ",{}]]},"cursor":{"x":41,"y":10}}],[0.025475,{"cursor":{"x":34,"y":9}}],[0.031082,{"cursor":{"x":38,"y":8}}],[0.029971,{"cursor":{"x":41,"y":7}}],[0.030525,{"cursor":{"x":0,"y":6}}],[0.02922,{"cursor":{"x":20,"y":5}}],[0.030453,{"cursor":{"x":30,"y":4}}],[0.030646,{"cursor":{"x":32,"y":3}}],[0.030453,{"cursor":{"x":34,"y":2}}],[0.03032,{"lines":{"2":[["<VirtualHost *:80>                                             ",{}]],"3":[["        ServerAdmin webmaster@localhost                        ",{}]],"4":[["        ServerName site1                                       ",{}]],"5":[["        DocumentRoot /home/darya/www/site1/                    ",{}]],"6":[["        <Directory />                                          ",{}]],"7":[["                Options FollowSymLinks                         ",{}]],"8":[["                AllowOverride None                             ",{}]],"9":[["        </Directory>                                           ",{}]],"10":[["        <Directory /home/darya/www/site1/>                     ",{}]],"11":[["                Options Indexes FollowSymLinks MultiViews      ",{}]],"12":[["                AllowOverride None                             ",{}]],"13":[["                Order allow,deny                               ",{}]],"14":[["                allow from all                                 ",{}]],"15":[["        </Directory>                                           ",{}]],"17":[["        ScriptAlias /cgi-bin/ /usr/lib/cgi-bin/                ",{}]],"18":[["        <Directory \"/usr/lib/cgi-bin\">                         ",{}]],"19":[["                AllowOverride None                             ",{}]],"20":[["                Options +ExecCGI -MultiViews +SymLinksIfOwnerM$",{}]]},"cursor":{"x":41,"y":11}}],[0.029978,{"cursor":{"y":10}}],[0.029319,{"cursor":{"x":20,"y":9}}],[0.031346,{"cursor":{"x":34,"y":8}}],[0.030072,{"cursor":{"x":38,"y":7}}],[0.029931,{"cursor":{"x":21,"y":6}}],[0.030294,{"cursor":{"x":41,"y":5}}],[2.922337,{"cursor":{"x":24,"y":4}}],[0.421914,{"cursor":{"x":39,"y":3}}],[0.28806,{"cursor":{"x":18,"y":2}}],[2.138849,{"lines":{"21":[["Сохранить изменённый буфер? (ИНАЧЕ ВСЕ ИЗМЕНЕНИЯ БУДУТ ПОТЕРЯН ",{"inverse":true}]],"22":[[" Y",{"inverse":true}],[" Да                                                          ",{}]],"23":[[" N",{"inverse":true}],[" Нет          ",{}],["^C",{"inverse":true}],[" Отмена                                      ",{}]]},"cursor":{"x":62,"y":21}}],[1.544118,{"lines":{"21":[["Имя файла для записи: /etc/apache2/sites-available/site1       ",{"inverse":true}]],"22":[["^G",{"inverse":true}],[" Помощь      ",{}],["M-D",{"inverse":true}],[" Формат DOS ",{}],["M-A",{"inverse":true}],[" Доп. в нача",{}],["M-B",{"inverse":true}],[" Резерв. копия ",{}]],"23":[["^C",{"inverse":true}],[" Отмена      ",{}],["M-M",{"inverse":true}],[" Формат Mac ",{}],["M-P",{"inverse":true}],[" Доп. в конец                 ",{}]]},"cursor":{"x":56}}],[0.9881760000000001,{"lines":{"0":[["darya@elena-VirtualBox:~$ mkdir www                            ",{}]],"1":[["darya@elena-VirtualBox:~$ cd www                               ",{}]],"2":[["darya@elena-VirtualBox:~/www$ mkdir site1                      ",{}]],"3":[["darya@elena-VirtualBox:~/www$ cd site1                         ",{}]],"4":[["darya@elena-VirtualBox:~/www/site1$ sudo nano info             ",{}]],"5":[["[sudo] password for darya:                                     ",{}]],"6":[["darya@elena-VirtualBox:~/www/site1$ cd ~                       ",{}]],"7":[["darya@elena-VirtualBox:~$ sudo cp /etc/apache2/sites-available/",{}]],"8":[["default /etc/apache2/sites-available/site1                     ",{}]],"9":[["darya@elena-VirtualBox:~$ sudo nano /etc/apache2/sites-availabl",{}]],"10":[["e/site1                                                        ",{}]],"11":[["                                                               ",{}]],"12":[["                                                               ",{}]],"13":[["                                                               ",{}]],"14":[["                                                               ",{}]],"15":[["                                                               ",{}]],"17":[["                                                               ",{}]],"18":[["                                                               ",{}]],"19":[["                                                               ",{}]],"20":[["                                                               ",{}]],"21":[["                                                               ",{}]],"22":[["                                                               ",{}]],"23":[["                                                               ",{}]]},"cursor":{"x":0,"y":11}}],[0.004092,{"lines":{"11":[["darya@elena-VirtualBox:~$                                      ",{}]]},"cursor":{"x":26}}],[3.413167,{"lines":{"11":[["darya@elena-VirtualBox:~$ s                                    ",{}]]},"cursor":{"x":27}}],[0.109436,{"lines":{"11":[["darya@elena-VirtualBox:~$ su                                   ",{}]]},"cursor":{"x":28}}],[0.124426,{"lines":{"11":[["darya@elena-VirtualBox:~$ sud                                  ",{}]]},"cursor":{"x":29}}],[0.882609,{"lines":{"11":[["darya@elena-VirtualBox:~$ sudo                                 ",{}]]},"cursor":{"x":30}}],[0.263007,{"cursor":{"x":31}}],[0.556617,{"lines":{"11":[["darya@elena-VirtualBox:~$ sudo a                               ",{}]]},"cursor":{"x":32}}],[0.361237,{"lines":{"11":[["darya@elena-VirtualBox:~$ sudo a2                              ",{}]]},"cursor":{"x":33}}],[1.060172,{}],[3.534133,{"lines":{"11":[["darya@elena-VirtualBox:~$ sudo a2e                             ",{}]]},"cursor":{"x":34}}],[0.175874,{"lines":{"11":[["darya@elena-VirtualBox:~$ sudo a2en                            ",{}]]},"cursor":{"x":35}}],[1.992305,{"lines":{"11":[["darya@elena-VirtualBox:~$ sudo a2ens                           ",{}]]},"cursor":{"x":36}}],[0.173433,{"lines":{"11":[["darya@elena-VirtualBox:~$ sudo a2ensi                          ",{}]]},"cursor":{"x":37}}],[0.756464,{"lines":{"11":[["darya@elena-VirtualBox:~$ sudo a2ensit                         ",{}]]},"cursor":{"x":38}}],[0.11701,{"lines":{"11":[["darya@elena-VirtualBox:~$ sudo a2ensite                        ",{}]]},"cursor":{"x":39}}],[0.653702,{"cursor":{"x":40}}],[0.215705,{"lines":{"11":[["darya@elena-VirtualBox:~$ sudo a2ensite s                      ",{}]]},"cursor":{"x":41}}],[0.210662,{"lines":{"11":[["darya@elena-VirtualBox:~$ sudo a2ensite si                     ",{}]]},"cursor":{"x":42}}],[0.319763,{"lines":{"11":[["darya@elena-VirtualBox:~$ sudo a2ensite sit                    ",{}]]},"cursor":{"x":43}}],[0.143954,{"lines":{"11":[["darya@elena-VirtualBox:~$ sudo a2ensite site                   ",{}]]},"cursor":{"x":44}}],[0.323105,{"lines":{"11":[["darya@elena-VirtualBox:~$ sudo a2ensite site1                  ",{}]]},"cursor":{"x":45}}],[0.498486,{"cursor":{"x":0,"y":12}}],[0.295224,{"lines":{"12":[["Enabling site site1.                                           ",{}]]},"cursor":{"x":20}}],[0.010107,{"lines":{"13":[["To activate the new configuration, you need to run:            ",{}]],"14":[["  service apache2 reload                                       ",{}]],"15":[["darya@elena-VirtualBox:~$                                      ",{}]]},"cursor":{"x":26,"y":15}}],[30.260518,{"lines":{"15":[["darya@elena-VirtualBox:~$ s                                    ",{}]]},"cursor":{"x":27}}],[0.152719,{"lines":{"15":[["darya@elena-VirtualBox:~$ su                                   ",{}]]},"cursor":{"x":28}}],[0.333433,{"lines":{"15":[["darya@elena-VirtualBox:~$ sud                                  ",{}]]},"cursor":{"x":29}}],[0.13393,{"lines":{"15":[["darya@elena-VirtualBox:~$ sudo                                 ",{}]]},"cursor":{"x":30}}],[0.137763,{"cursor":{"x":31}}],[0.440064,{"lines":{"15":[["darya@elena-VirtualBox:~$ sudo n                               ",{}]]},"cursor":{"x":32}}],[0.055641,{"lines":{"15":[["darya@elena-VirtualBox:~$ sudo na                              ",{}]]},"cursor":{"x":33}}],[0.126769,{"lines":{"15":[["darya@elena-VirtualBox:~$ sudo nan                             ",{}]]},"cursor":{"x":34}}],[0.261179,{"lines":{"15":[["darya@elena-VirtualBox:~$ sudo nano                            ",{}]]},"cursor":{"x":35}}],[2.581289,{"cursor":{"x":36}}],[0.512293,{"lines":{"15":[["darya@elena-VirtualBox:~$ sudo nano /                          ",{}]]},"cursor":{"x":37}}],[0.485399,{"lines":{"15":[["darya@elena-VirtualBox:~$ sudo nano /e                         ",{}]]},"cursor":{"x":38}}],[0.290808,{"lines":{"15":[["darya@elena-VirtualBox:~$ sudo nano /etc/                      ",{}]]},"cursor":{"x":41}}],[1.936612,{"lines":{"15":[["darya@elena-VirtualBox:~$ sudo nano /etc/h                     ",{}]]},"cursor":{"x":42}}],[0.276553,{}],[1.46498,{"lines":{"15":[["darya@elena-VirtualBox:~$ sudo nano /etc/ho                    ",{}]]},"cursor":{"x":43}}],[0.360472,{}],[0.000142,{"lines":{"15":[["darya@elena-VirtualBox:~$ sudo nano /etc/host                  ",{}]]},"cursor":{"x":45}}],[2.593497,{"lines":{"15":[["darya@elena-VirtualBox:~$ sudo nano /etc/hosts                 ",{}]]},"cursor":{"x":46}}],[1.594005,{"cursor":{"x":0,"y":16}}],[0.01664,{"lines":{"0":[["  GNU nano 2.2.6        Файл: /etc/hosts                       ",{"inverse":true}]],"1":[["                                                               ",{}]],"2":[["127.0.0.1       localhost                                      ",{}]],"3":[["127.0.1.1       elena-VirtualBox                               ",{}]],"4":[["                                                               ",{}]],"5":[["# The following lines are desirable for IPv6 capable hosts     ",{}]],"6":[["::1     ip6-localhost ip6-loopback                             ",{}]],"7":[["fe00::0 ip6-localnet                                           ",{}]],"8":[["ff00::0 ip6-mcastprefix                                        ",{}]],"9":[["ff02::1 ip6-allnodes                                           ",{}]],"10":[["ff02::2 ip6-allrouters                                         ",{}]],"11":[["                                                               ",{}]],"12":[["                                                               ",{}]],"13":[["                                                               ",{}]],"14":[["                                                               ",{}]],"15":[["                                                               ",{}]],"21":[["                     ",{}],["[ Прочитано 9 строк ]",{"inverse":true}],["                     ",{}]],"22":[["^G",{"inverse":true}],[" Помощь ",{}],["^O",{"inverse":true}],[" Записат",{}],["^R",{"inverse":true}],[" ЧитФайл",{}],["^Y",{"inverse":true}],[" ПредCтр",{}],["^K",{"inverse":true}],[" Вырезат",{}],["^C",{"inverse":true}],[" ТекПозиц  ",{}]],"23":[["^X",{"inverse":true}],[" Выход  ",{}],["^J",{"inverse":true}],[" Выровня",{}],["^W",{"inverse":true}],[" Поиск  ",{}],["^V",{"inverse":true}],[" СледCтр",{}],["^U",{"inverse":true}],[" ОтмВыре",{}],["^T",{"inverse":true}],[" Словарь   ",{}]]},"cursor":{"y":2}}],[2.14072,{"cursor":{"y":3}}],[1.169035,{"cursor":{"y":4}}],[1.753855,{"lines":{"0":[["  GNU nano 2.2.6        Файл: /etc/hosts              Изменён  ",{"inverse":true}]],"4":[["1                                                              ",{}]]},"cursor":{"x":1}}],[0.088462,{"lines":{"4":[["12                                                             ",{}]]},"cursor":{"x":2}}],[0.30192,{"lines":{"4":[["127                                                            ",{}]]},"cursor":{"x":3}}],[0.495989,{"lines":{"4":[["127.                                                           ",{}]]},"cursor":{"x":4}}],[0.179068,{"lines":{"4":[["127.0                                                          ",{}]]},"cursor":{"x":5}}],[1.008059,{"lines":{"4":[["127.0.                                                         ",{}]]},"cursor":{"x":6}}],[0.277268,{"lines":{"4":[["127.0.1                                                        ",{}]]},"cursor":{"x":7}}],[0.313062,{"lines":{"4":[["127.0.1.                                                       ",{}]]},"cursor":{"x":8}}],[0.297921,{"lines":{"4":[["127.0.1.2                                                      ",{}]]},"cursor":{"x":9}}],[2.293894,{"cursor":{"x":16}}],[0.630504,{"lines":{"4":[["127.0.1.2       s                                              ",{}]]},"cursor":{"x":17}}],[0.274127,{"lines":{"4":[["127.0.1.2       si                                             ",{}]]},"cursor":{"x":18}}],[0.379895,{"lines":{"4":[["127.0.1.2       sit                                            ",{}]]},"cursor":{"x":19}}],[0.094426,{"lines":{"4":[["127.0.1.2       site                                           ",{}]]},"cursor":{"x":20}}],[0.324733,{"lines":{"4":[["127.0.1.2       site1                                          ",{}]]},"cursor":{"x":21}}],[3.574263,{"lines":{"5":[["                                                               ",{}]],"6":[["# The following lines are desirable for IPv6 capable hosts     ",{}]],"7":[["::1     ip6-localhost ip6-loopback                             ",{}]],"8":[["fe00::0 ip6-localnet                                           ",{}]],"9":[["ff00::0 ip6-mcastprefix                                        ",{}]],"10":[["ff02::1 ip6-allnodes                                           ",{}]],"11":[["ff02::2 ip6-allrouters                                         ",{}]]},"cursor":{"x":0,"y":5}}],[1.418175,{"lines":{"21":[["Сохранить изменённый буфер? (ИНАЧЕ ВСЕ ИЗМЕНЕНИЯ БУДУТ ПОТЕРЯН ",{"inverse":true}]],"22":[[" Y",{"inverse":true}],[" Да                                                          ",{}]],"23":[[" N",{"inverse":true}],[" Нет          ",{}],["^C",{"inverse":true}],[" Отмена                                      ",{}]]},"cursor":{"x":62,"y":21}}],[1.093254,{"lines":{"21":[["Имя файла для записи: /etc/hosts                               ",{"inverse":true}]],"22":[["^G",{"inverse":true}],[" Помощь      ",{}],["M-D",{"inverse":true}],[" Формат DOS ",{}],["M-A",{"inverse":true}],[" Доп. в нача",{}],["M-B",{"inverse":true}],[" Резерв. копия ",{}]],"23":[["^C",{"inverse":true}],[" Отмена      ",{}],["M-M",{"inverse":true}],[" Формат Mac ",{}],["M-P",{"inverse":true}],[" Доп. в конец                 ",{}]]},"cursor":{"x":32}}],[0.678078,{"lines":{"0":[["  GNU nano 2.2.6        Файл: /etc/hosts                       ",{"inverse":true}]],"21":[["                     ",{}],["[ Записано 10 строк ]",{"inverse":true}],["                     ",{}]],"22":[["                                                               ",{}]],"23":[["                                                               ",{}]]},"cursor":{"x":62,"y":23}}],[0.008410000000000001,{"lines":{"0":[["darya@elena-VirtualBox:~$ mkdir www                            ",{}]],"1":[["darya@elena-VirtualBox:~$ cd www                               ",{}]],"2":[["darya@elena-VirtualBox:~/www$ mkdir site1                      ",{}]],"3":[["darya@elena-VirtualBox:~/www$ cd site1                         ",{}]],"4":[["darya@elena-VirtualBox:~/www/site1$ sudo nano info             ",{}]],"5":[["[sudo] password for darya:                                     ",{}]],"6":[["darya@elena-VirtualBox:~/www/site1$ cd ~                       ",{}]],"7":[["darya@elena-VirtualBox:~$ sudo cp /etc/apache2/sites-available/",{}]],"8":[["default /etc/apache2/sites-available/site1                     ",{}]],"9":[["darya@elena-VirtualBox:~$ sudo nano /etc/apache2/sites-availabl",{}]],"10":[["e/site1                                                        ",{}]],"11":[["darya@elena-VirtualBox:~$ sudo a2ensite site1                  ",{}]],"12":[["Enabling site site1.                                           ",{}]],"13":[["To activate the new configuration, you need to run:            ",{}]],"14":[["  service apache2 reload                                       ",{}]],"15":[["darya@elena-VirtualBox:~$ sudo nano /etc/hosts                 ",{}]],"16":[["darya@elena-VirtualBox:~$                                      ",{}]],"21":[["                                                               ",{}]]},"cursor":{"x":26,"y":16}}],[5.923691,{"lines":{"16":[["darya@elena-VirtualBox:~$ e                                    ",{}]]},"cursor":{"x":27}}],[0.252552,{"lines":{"16":[["darya@elena-VirtualBox:~$ ex                                   ",{}]]},"cursor":{"x":28}}],[0.163462,{"lines":{"16":[["darya@elena-VirtualBox:~$ exi                                  ",{}]]},"cursor":{"x":29}}],[0.168759,{"lines":{"16":[["darya@elena-VirtualBox:~$ exit                                 ",{}]]},"cursor":{"x":30}}],[0.631082,{"lines":{"17":[["exit                                                           ",{}]]},"cursor":{"x":0,"y":18}}]]